ex1-2/counter.v
module counter(clk, rst, count);

 input clk;
 input rst;
 output [6:0] count;

 reg [6:0] count_reg;

 always @(posedge clk or posedge rst) begin
  if (rst)
  count_reg <= 7'b0000000;
  else begin
    if (count_reg == 7'd100)
      count_reg <= 7'b0000000;
    else
      count_reg <= count_reg +1;

  end
 end
 assign count = count_reg;

 endmodule

ex1-2/test_counter.v
`timescale 1ps / 1ps
module test_counter();
parameter CLK = 1000000/10; // 10MHz
// for input
reg clk; reg rst;
// for output
wire [6:0] count;
// module
  counter counter0(
.clk (clk), .rst (rst), .count(count));
// clock generation
always begin
clk = 1'b1;
#(CLK/2); clk = 1'b0;
#(CLK/2);
end

// test senario
initial begin
  $dumpfile("test_counter.vcd");
  $dumpvars(1, test_counter);
rst = 1;
#(CLK); rst = 0;
#(CLK*120); rst = 1;
#(CLK*10);
$finish;
end
endmodule

ex1-2/test_counter.vcd
$date
	Sun May 14 15:14:12 2023
$end
$version
	Icarus Verilog
$end
$timescale
	1ps
$end
$scope module test_counter $end
$var wire 7 ! count [6:0] $end
$var reg 1 " clk $end
$var reg 1 # rst $end
$upscope $end
$enddefinitions $end
#0
$dumpvars
1#
1"
b0 !
$end
#50000
0"
#100000
b1 !
1"
0#
#150000
0"
#200000
b10 !
1"
#250000
0"
#300000
b11 !
1"
#350000
0"
#400000
b100 !
1"
#450000
0"
#500000
b101 !
1"
#550000
0"
#600000
b110 !
1"
#650000
0"
#700000
b111 !
1"
#750000
0"
#800000
b1000 !
1"
#850000
0"
#900000
b1001 !
1"
#950000
0"
#1000000
b1010 !
1"
#1050000
0"
#1100000
b1011 !
1"
#1150000
0"
#1200000
b1100 !
1"
#1250000
0"
#1300000
b1101 !
1"
#1350000
0"
#1400000
b1110 !
1"
#1450000
0"
#1500000
b1111 !
1"
#1550000
0"
#1600000
b10000 !
1"
#1650000
0"
#1700000
b10001 !
1"
#1750000
0"
#1800000
b10010 !
1"
#1850000
0"
#1900000
b10011 !
1"
#1950000
0"
#2000000
b10100 !
1"
#2050000
0"
#2100000
b10101 !
1"
#2150000
0"
#2200000
b10110 !
1"
#2250000
0"
#2300000
b10111 !
1"
#2350000
0"
#2400000
b11000 !
1"
#2450000
0"
#2500000
b11001 !
1"
#2550000
0"
#2600000
b11010 !
1"
#2650000
0"
#2700000
b11011 !
1"
#2750000
0"
#2800000
b11100 !
1"
#2850000
0"
#2900000
b11101 !
1"
#2950000
0"
#3000000
b11110 !
1"
#3050000
0"
#3100000
b11111 !
1"
#3150000
0"
#3200000
b100000 !
1"
#3250000
0"
#3300000
b100001 !
1"
#3350000
0"
#3400000
b100010 !
1"
#3450000
0"
#3500000
b100011 !
1"
#3550000
0"
#3600000
b100100 !
1"
#3650000
0"
#3700000
b100101 !
1"
#3750000
0"
#3800000
b100110 !
1"
#3850000
0"
#3900000
b100111 !
1"
#3950000
0"
#4000000
b101000 !
1"
#4050000
0"
#4100000
b101001 !
1"
#4150000
0"
#4200000
b101010 !
1"
#4250000
0"
#4300000
b101011 !
1"
#4350000
0"
#4400000
b101100 !
1"
#4450000
0"
#4500000
b101101 !
1"
#4550000
0"
#4600000
b101110 !
1"
#4650000
0"
#4700000
b101111 !
1"
#4750000
0"
#4800000
b110000 !
1"
#4850000
0"
#4900000
b110001 !
1"
#4950000
0"
#5000000
b110010 !
1"
#5050000
0"
#5100000
b110011 !
1"
#5150000
0"
#5200000
b110100 !
1"
#5250000
0"
#5300000
b110101 !
1"
#5350000
0"
#5400000
b110110 !
1"
#5450000
0"
#5500000
b110111 !
1"
#5550000
0"
#5600000
b111000 !
1"
#5650000
0"
#5700000
b111001 !
1"
#5750000
0"
#5800000
b111010 !
1"
#5850000
0"
#5900000
b111011 !
1"
#5950000
0"
#6000000
b111100 !
1"
#6050000
0"
#6100000
b111101 !
1"
#6150000
0"
#6200000
b111110 !
1"
#6250000
0"
#6300000
b111111 !
1"
#6350000
0"
#6400000
b1000000 !
1"
#6450000
0"
#6500000
b1000001 !
1"
#6550000
0"
#6600000
b1000010 !
1"
#6650000
0"
#6700000
b1000011 !
1"
#6750000
0"
#6800000
b1000100 !
1"
#6850000
0"
#6900000
b1000101 !
1"
#6950000
0"
#7000000
b1000110 !
1"
#7050000
0"
#7100000
b1000111 !
1"
#7150000
0"
#7200000
b1001000 !
1"
#7250000
0"
#7300000
b1001001 !
1"
#7350000
0"
#7400000
b1001010 !
1"
#7450000
0"
#7500000
b1001011 !
1"
#7550000
0"
#7600000
b1001100 !
1"
#7650000
0"
#7700000
b1001101 !
1"
#7750000
0"
#7800000
b1001110 !
1"
#7850000
0"
#7900000
b1001111 !
1"
#7950000
0"
#8000000
b1010000 !
1"
#8050000
0"
#8100000
b1010001 !
1"
#8150000
0"
#8200000
b1010010 !
1"
#8250000
0"
#8300000
b1010011 !
1"
#8350000
0"
#8400000
b1010100 !
1"
#8450000
0"
#8500000
b1010101 !
1"
#8550000
0"
#8600000
b1010110 !
1"
#8650000
0"
#8700000
b1010111 !
1"
#8750000
0"
#8800000
b1011000 !
1"
#8850000
0"
#8900000
b1011001 !
1"
#8950000
0"
#9000000
b1011010 !
1"
#9050000
0"
#9100000
b1011011 !
1"
#9150000
0"
#9200000
b1011100 !
1"
#9250000
0"
#9300000
b1011101 !
1"
#9350000
0"
#9400000
b1011110 !
1"
#9450000
0"
#9500000
b1011111 !
1"
#9550000
0"
#9600000
b1100000 !
1"
#9650000
0"
#9700000
b1100001 !
1"
#9750000
0"
#9800000
b1100010 !
1"
#9850000
0"
#9900000
b1100011 !
1"
#9950000
0"
#10000000
b1100100 !
1"
#10050000
0"
#10100000
b0 !
1"
#10150000
0"
#10200000
b1 !
1"
#10250000
0"
#10300000
b10 !
1"
#10350000
0"
#10400000
b11 !
1"
#10450000
0"
#10500000
b100 !
1"
#10550000
0"
#10600000
b101 !
1"
#10650000
0"
#10700000
b110 !
1"
#10750000
0"
#10800000
b111 !
1"
#10850000
0"
#10900000
b1000 !
1"
#10950000
0"
#11000000
b1001 !
1"
#11050000
0"
#11100000
b1010 !
1"
#11150000
0"
#11200000
b1011 !
1"
#11250000
0"
#11300000
b1100 !
1"
#11350000
0"
#11400000
b1101 !
1"
#11450000
0"
#11500000
b1110 !
1"
#11550000
0"
#11600000
b1111 !
1"
#11650000
0"
#11700000
b10000 !
1"
#11750000
0"
#11800000
b10001 !
1"
#11850000
0"
#11900000
b10010 !
1"
#11950000
0"
#12000000
b10011 !
1"
#12050000
0"
#12100000
b0 !
1"
1#
