ex1-1/fsm.v
module fsm(clk, start, stop, mode, state);

input clk;
input start;
input stop;
input mode;
output [1:0] state;

reg [1:0] st_reg = 2'd0;

// state name
parameter INIT = 2'd0;
parameter RUN = 2'd1;
parameter WAIT = 2'd2;

always @(posedge clk) begin
if (st_reg == INIT && start == 1)
 st_reg <= RUN;

if (st_reg == RUN && mode == 1)
 st_reg <= INIT;
 else if (st_reg == RUN && mode == 0)
 st_reg <= WAIT;

if (st_reg == WAIT && stop == 1)
st_reg <= INIT;

end

assign state = st_reg;

endmodule

ex1-1/test_fsm.v
`timescale 1ps / 1ps
module test_fsm();
parameter CLK = 1000000/10; // 10MHz
// for input
reg clk; reg start; reg stop; reg mode;
// for output
wire [1:0] state;
// module
  fsm fsm0(
.clk (clk), .start (start), .stop (stop), .mode (mode), .state (state) );
// clock generation
always begin
clk = 1'b1; #(CLK/2); clk = 1'b0; #(CLK/2);
end

// test senario
initial begin
  $dumpfile("test_fsm.vcd");
  $dumpvars(1, test_fsm);
start = 0; stop = 0;mode = 0;
#(CLK/2); start = 1;
#(CLK); mode = 1;
#(CLK*2); mode = 0;
#(CLK*2); stop = 1;
#(CLK);
$finish;
end
endmodule

ex1-1/test_fsm.vcd
$date
	Mon May 15 17:41:31 2023
$end
$version
	Icarus Verilog
$end
$timescale
	1ps
$end
$scope module test_fsm $end
$var wire 2 ! state [1:0] $end
$var reg 1 " clk $end
$var reg 1 # mode $end
$var reg 1 $ start $end
$var reg 1 % stop $end
$upscope $end
$enddefinitions $end
#0
$dumpvars
0%
0$
0#
1"
b0 !
$end
#50000
1$
0"
#100000
b1 !
1"
#150000
0"
1#
#200000
b0 !
1"
#250000
0"
#300000
b1 !
1"
#350000
0"
0#
#400000
b10 !
1"
#450000
0"
1%
#500000
b0 !
1"
#550000
0"
#600000
b1 !
1"
#650000
0"
#700000
b10 !
1"
