ex1-1/fsm.v
module fsm(clk, xrst, start, stop, mode, state);

input clk;
input xrst;
input start;
input stop;
input mode;
output [1:0] state;

reg [1:0] st_reg;

// state name
parameter INIT = 2'd0;
parameter RUN = 2'd1;
parameter WAIT = 2'd2;

always @(posedge clk or negedge xrst) begin
if (st_reg == INIT && start == 1)
 st_reg <= RUN;

if (st_reg == RUN && mode == 1)
 st_reg <= INIT;
 else if (st_reg == RUN && mode == 0)
 st_reg <= WAIT;

if (st_reg == WAIT && stop == 1)
st_reg <= INIT;

if (!xrst)
st_reg <= INIT;
end

assign state = st_reg;

endmodule

ex1-1/test_fsm.v
`timescale 1ps / 1ps
module test_fsm();
parameter CLK = 1000000/10; // 10MHz
// for input
reg clk; reg xrst; reg start; reg stop; reg mode;
// for output
wire [1:0] state;
// module
  fsm fsm0(
.clk (clk), .xrst (xrst), .start (start), .stop (stop), .mode (mode), .state (state) );
// clock generation
always begin
clk = 1'b1; #(CLK/2); clk = 1'b0; #(CLK/2);
end

// test senario
initial begin
  $dumpfile("test_fsm.vcd");
  $dumpvars(1, test_fsm);
xrst = 1; start = 0; stop = 0;
#(CLK/2); xrst = 0;
#(CLK); xrst = 1;
// mode 0
mode = 0;
#(CLK); start = 1;
#(CLK); start = 0;
#(CLK*3); stop = 1;
#(CLK); stop = 0;
#(CLK*3);
// mode 1
mode = 1;
#(CLK); start = 1;
#(CLK); start = 0;
#(CLK*3);
$finish;
end
endmodule

ex1-1/test_fsm.vcd
$date
	Sun May 14 14:42:40 2023
$end
$version
	Icarus Verilog
$end
$timescale
	1ps
$end
$scope module test_fsm $end
$var wire 2 ! state [1:0] $end
$var reg 1 " clk $end
$var reg 1 # mode $end
$var reg 1 $ start $end
$var reg 1 % stop $end
$var reg 1 & xrst $end
$upscope $end
$enddefinitions $end
#0
$dumpvars
1&
0%
0$
x#
1"
bx !
$end
#50000
b0 !
0&
0"
#100000
1"
#150000
0"
0#
1&
#200000
1"
#250000
0"
1$
#300000
b1 !
1"
#350000
0"
0$
#400000
b10 !
1"
#450000
0"
#500000
1"
#550000
0"
#600000
1"
#650000
0"
1%
#700000
b0 !
1"
#750000
0"
0%
#800000
1"
#850000
0"
#900000
1"
#950000
0"
#1000000
1"
#1050000
0"
1#
#1100000
1"
#1150000
0"
1$
#1200000
b1 !
1"
#1250000
0"
0$
#1300000
b0 !
1"
